{
  "users": [
    {
      "id": 1,
      "userName": "Petike",
      "userAge": 23
    },
    {
      "id": 3,
      "userName": "Juli",
      "userAge": 17
    },
    {
      "id": 4,
      "userName": "Mari",
      "userAge": 69
    },
    {
      "id": 5,
      "userName": "Tibi",
      "userAge": 42
    },
    {
      "id": 6,
      "userName": "Kati",
      "userAge": 87
    },
    {
      "id": 8,
      "userName": "Teri",
      "userAge": 76
    },
    {
      "id": 9,
      "userName": "Józsi",
      "userAge": 34
    },
    {
      "userName": "Jani",
      "userAge": 44,
      "id": 11
    },
    {
      "userName": "Dorottya",
      "userAge": 22,
      "id": 12
    },
    {
      "userName": "Majom",
      "userAge": 77,
      "id": 13
    },
    {
      "userName": "Zotlán",
      "userAge": 22,
      "id": 14
    }
  ],
  "comments": [
    {
      "id": 1,
      "content": "zsír",
      "userID": 1
    },
    {
      "id": 2,
      "content": "jó",
      "userID": 5
    },
    {
      "id": 3,
      "content": "tetszik",
      "userID": 7
    },
    {
      "id": 4,
      "content": "elég fos",
      "userID": 3
    }
  ]
}